[{"url":"https://news.joysound.com/article/670039","date":"2026-04-29T08:32:00.000Z","category":"週末・イベント","short_title":"お台場アイドルフェス","original_title":"「TIF」初登場の8組がメインステージ出演をかけて激突 - JOYSOUND 音楽ニュース"},{"url":"https://news.yahoo.co.jp/articles/ae4857f3853e0b9e6654a4eec40083a9920cad3e","date":"2026-04-29T08:32:00.000Z","category":"湾岸ライフ","short_title":"豊洲にウイルソン開店","original_title":"いま欲しいのは、スポーツ由来の洗練ワードローブ 〈ウイルソン〉が豊洲に国内2号店をオープン！ - Yahoo!ニュース"},{"url":"https://www.faith-wonderworks.co.jp/jsp/artist/news_gp.jsp?index=barks&key=1063851&aid=107055","date":"2026-04-29T08:32:00.000Z","category":"週末・イベント","short_title":"平井大が有明ライブ","original_title":"東京・SGCホール有明で＜HIRAIDAI LOCALS ONLY SPECIAL LIVE＞開催。新曲3曲の連続 ... - faith-wonderworks.co.jp"},{"url":"https://article.auone.jp/detail/1/6/12/202_12_r_20260428_1777332691929647","date":"2026-04-29T08:32:00.000Z","category":"週末・イベント","short_title":"有明アリーナで格闘技","original_title":"武尊、「２回までボクシング」ロッタン「不敵」予告に動じず…「しゃべる言葉は全く気にして ... - au Webポータル"},{"url":"https://fineplay.me/others/138031/","date":"2026-04-29T08:32:00.000Z","category":"週末・イベント","short_title":"豊洲ストリートフェス","original_title":"GWの豊洲でアーバンスポーツが集結！『TOYOSU STREET PARK FES』5月2日 - FINEPLAY"},{"url":"https://lp.p.pia.jp/article/news/473636/index.html?detail=true","date":"2026-04-29T08:32:00.000Z","category":"週末・イベント","short_title":"有明の新劇場が開業","original_title":"新劇場の幕開けを飾るスペクタクル『AmberS-アンバース-』、感情を揺さぶる物語が始動 - ぴあエンタメ情報"},{"url":"https://eiga.com/news/20260427/18/","date":"2026-04-29T08:32:00.000Z","category":"週末・イベント","short_title":"目黒蓮が豊洲に登場","original_title":"Snow Man目黒蓮、主演映画プロモーションのため緊急帰国！「カナダから帰ってきてしまいまし ... - 映画.com"},{"url":"https://www.youtube.com/watch?v=1skRFuCtYUM","date":"2026-04-29T08:32:00.000Z","category":"週末・イベント","short_title":"豊洲でマリオイベント","original_title":"【神対応】ザ・スーパーマリオギャラクシームービー限定コラボ！豊洲イベントでスタッフさんに ... - YouTube"},{"url":"https://abema.tv/video/episode/89-42_s0_p501328","date":"2026-04-29T08:32:00.000Z","category":"まちの資産価値","short_title":"日本橋ー豊洲の定期船","original_title":"日本橋ー豊洲間の定期船運航開始 通勤や買い物での利用に期待 Wi-Fiも完備 - ABEMA"},{"url":"https://news.yahoo.co.jp/articles/e4df5315ba2c4f775573e7c1421faec8ae7fd3cd","date":"2026-04-29T08:32:00.000Z","category":"湾岸ライフ","short_title":"有明に新エンタメ施設","original_title":"有明に誕生した複合型エンタテインメント施設「TOKYO DREAM PARK」！5月 ... - Yahoo!ニュース"},{"url":"https://news.livedoor.com/topics/detail/31104931/","date":"2026-04-28T08:33:00.000Z","category":"まちの資産価値","short_title":"中央区の世帯増に異変","original_title":"東京・中央区で世帯増加に急ブレーキ「湾岸バブル」失速の兆し - ライブドアニュース"},{"url":"https://news.ameba.jp/entry/20260427-75666763/","date":"2026-04-28T08:33:00.000Z","category":"週末・イベント","short_title":"有明に新エンタメ施設","original_title":"有明に誕生した複合型エンタテインメント施設「TOKYO DREAM PARK」！5月10日まで開業記念 ..."},{"url":"https://marieclairejapon.com/lifestyle/279685/","date":"2026-04-28T08:33:00.000Z","category":"湾岸ライフ","short_title":"お台場ホテル限定夕食","original_title":"「ヒルトン東京お台場」で東京アクアシンフォニーを満喫。炭火焼き料理がセットになった特別 ..."},{"url":"https://www.jiji.com/jc/article?k=000000032.000133380&g=prt","date":"2026-04-28T08:33:00.000Z","category":"愛犬と暮らす","short_title":"有明で愛犬ギネス挑戦","original_title":"【人と犬の豊かな共生社会を目指して】愛犬と飼い主が挑む『ギネス世界記録(TM)』！「ロンドン ..."},{"url":"https://news.yahoo.co.jp/articles/c5ec6969b49c59e477e00ff4c99696beddc1932e","date":"2026-04-28T08:33:00.000Z","category":"週末・イベント","short_title":"お台場に肉フェス上陸","original_title":"GWは肉を喰らえ！お台場で12日間行われる肉祭り！「肉フェス(R)2026 TOKYO JAPAN ..."},{"url":"https://x.com/eggsn_harajuku/status/2048904536019157042","date":"2026-04-28T08:33:00.000Z","category":"湾岸ライフ","short_title":"豊洲にエッグスン開店","original_title":"【 本日 10:00 GRAND OPEN 】 Eggs 'n Thingsが東京湾岸エリア最大級『アーバンドック ..."},{"url":"https://tennis-blog.net/2026/04/25/%E5%9B%BD%E5%86%852%E5%BA%97%E8%88%97%E7%9B%AE%EF%BC%81%E3%80%90wilson%E3%80%91%E3%82%A2%E3%83%BC%E3%83%90%E3%83%B3%E3%83%89%E3%83%83%E3%82%AF-%E3%82%89%E3%82%89%E3%81%BD%E3%83%BC%E3%81%A8%E8%B1%8A/","date":"2026-04-28T08:33:00.000Z","category":"湾岸ライフ","short_title":"豊洲にWilson開店","original_title":"国内2店舗目！【Wilson】アーバンドック ららぽーと豊洲にブランドストアがオープン！プレ ..."},{"url":"https://spring.walkerplus.com/gw/topics/article/1339212/image16595071.html","date":"2026-04-28T08:33:00.000Z","category":"週末・イベント","short_title":"有明にエンタメ施設誕生","original_title":"有明に誕生した複合型エンタテインメント施設「TOKYO DREAM PARK」！5月10日まで開業記念 ..."},{"url":"https://x.com/kachidokitoyomi/status/2048886005755998495","date":"2026-04-28T08:33:00.000Z","category":"湾岸ライフ","short_title":"晴海フラッグバスと閉店時間","original_title":"晴海フラッグの飲食店はBRTと都バスの終バスが22時18,9分だから22時閉店なんですかね 勝どき ..."},{"url":"https://topics.smt.docomo.ne.jp/amp/article/nikkangeinou/entertainment/f-et-tp0-260426-202604260001237","date":"2026-04-28T08:33:00.000Z","category":"週末・イベント","short_title":"豊洲で新グループ","original_title":"秋元康氏、新ボーイズグループ「Cloud ten」初イベント終え「すごく緊張しましたが…」"},{"url":"http://www.labornetjp.org/EventItem/1777249043188staff01","date":"2026-04-28T08:33:00.000Z","category":"週末・イベント","short_title":"月島で平和の展示","original_title":"「平和をねがう中央区民の戦争展2026」（8月15 - レイバーネット"},{"url":"https://natalie.mu/music/news/666627","date":"2026-04-28T08:32:00.000Z","category":"週末・イベント","short_title":"有明ライブバトル","original_title":"超特急、BALLISTIK BOYZ、MAZZEL、TAGRIGHTが楽曲交換バトル！グループの垣根を超えた ..."},{"url":"https://news.tv-asahi.co.jp/news_society/articles/900189274.html","date":"2026-04-28T08:32:00.000Z","category":"湾岸ライフ","short_title":"日本橋-豊洲定期船","original_title":"日本橋ー豊洲間の定期船運航開始 通勤や買い物での利用に期待 Wi-Fiも完備 - テレ朝NEWS"},{"url":"https://edmmaxx.com/news/61399","date":"2026-04-28T08:32:00.000Z","category":"週末・イベント","short_title":"お台場ULTRA","original_title":"ULTRA JAPAN 2026 第1弾ラインナップ発表 – 10周年を経て、“次のダンスミュージック”が東京へ"},{"url":"https://entamerush.jp/683760/","date":"2026-04-28T08:32:00.000Z","category":"週末・イベント","short_title":"歌舞伎と築地料理","original_title":"五感を揺さぶる超貴重体験！ ～シネマ歌舞伎『京鹿子娘二人道成寺』上映 × 手にとれる「歌舞伎の小道具」解説 × 築地イタリアン"},{"url":"https://news.yahoo.co.jp/articles/55b65163a993f3dc6a403b3e23a352e1a6ed0120","date":"2026-04-28T08:32:00.000Z","category":"こどもと暮らす","short_title":"ドラえもん最大展","original_title":"「100％ドラえもん＆フレンズ in 東京」世界各地を巡ったドラえもん史上最大級のイベントが ..."},{"url":"https://diskgarage.com/digaonline/news/231504?amp=1","date":"2026-04-28T08:32:00.000Z","category":"週末・イベント","short_title":"お台場音楽フェス","original_title":"TOKYO ISLAND 2026、10/10(土)、11(日)、12(月祝)に開催決定！第一弾出演者アーティストに ..."},{"url":"https://www.tbs.co.jp/tv/20260504_AADD.html","date":"2026-04-28T08:32:00.000Z","category":"こどもと暮らす","short_title":"豊洲で没入型体験","original_title":"映画『モンスターズ・インク』[字] - TBSテレビ"},{"url":"https://koto.keizai.biz/headline/854/","date":"2026-04-28T08:32:00.000Z","category":"週末・イベント","short_title":"隅田川マルシェ","original_title":"江東・越中島で春の「隅田川マルシェ」 クルーズやトレーラーハウス内覧も"},{"url":"https://news.yahoo.co.jp/articles/e4df5315ba2c4f775573e7c1421faec8ae7fd3cd","date":"2026-04-28T08:32:00.000Z","category":"週末・イベント","short_title":"有明で春祭り開催","original_title":"有明に誕生した複合型エンタテインメント施設「TOKYO DREAM PARK」！5月 ... - Yahoo!ニュース"}]